<?xml version="1.0" encoding="UTF-8"?>
<!DOCTYPE hibernate-mapping PUBLIC "-//Hibernate/Hibernate Mapping DTD 3.0//EN" "http://hibernate.sourceforge.net/hibernate-mapping-3.0.dtd">
<!-- Generated Jun 17, 2011 1:34:28 AM by Hibernate Tools 3.2.1.GA -->
<hibernate-mapping>
  <class catalog="itp" lazy="false" name="com.itp.dao.entity.TicketAttachement" table="ticket_attachement">
    <id name="ticketAttachement" type="java.lang.Integer">
      <column name="ticket_attachement"/>
      <generator class="identity"/>
    </id>
    <property name="fileRecordId" type="int">
      <column name="file_record_id" not-null="true"/>
    </property>
    <property name="ticketDetailId" type="int">
      <column name="ticket_detail_id" not-null="true"/>
    </property>
  </class>
</hibernate-mapping>
